dora_cli/__init__.py
dora_cli/__main__.py
dora_cli/aws.py
dora_cli/config.py
dora_cli/hwc.py
dora_cli-0.0.5.dist-info/LICENSE
dora_cli-0.0.5.dist-info/WHEEL
dora_cli-0.0.5.dist-info/METADATA
dora_cli-0.0.5.dist-info/RECORD
